{"prefix": "rand3reg_12_1_pysat", "layers": [{"qubits": [{"id": 0, "a": 1, "x": 0, "y": 12, "c": 6, "r": 11}, {"id": 1, "a": 0, "x": 1, "y": 7, "c": 10, "r": 13}, {"id": 2, "a": 1, "x": 0, "y": 12, "c": 5, "r": 10}, {"id": 3, "a": 1, "x": 1, "y": 4, "c": 8, "r": 2}, {"id": 4, "a": 1, "x": 0, "y": 11, "c": 4, "r": 8}, {"id": 5, "a": 1, "x": 0, "y": 11, "c": 6, "r": 9}, {"id": 6, "a": 1, "x": 1, "y": 7, "c": 7, "r": 3}, {"id": 7, "a": 1, "x": 0, "y": 4, "c": 6, "r": 2}, {"id": 8, "a": 0, "x": 0, "y": 4, "c": 2, "r": 1}, {"id": 9, "a": 1, "x": 0, "y": 8, "c": 5, "r": 6}, {"id": 10, "a": 0, "x": 1, "y": 4, "c": 9, "r": 5}, {"id": 11, "a": 1, "x": 0, "y": 8, "c": 6, "r": 4}], "gates": [{"id": 2, "q0": 9, "q1": 11}, {"id": 3, "q0": 3, "q1": 10}, {"id": 6, "q0": 0, "q1": 2}, {"id": 9, "q0": 1, "q1": 6}, {"id": 14, "q0": 4, "q1": 5}, {"id": 17, "q0": 7, "q1": 8}]}, {"qubits": [{"id": 0, "a": 1, "x": 2, "y": 7, "c": 6, "r": 11}, {"id": 1, "a": 0, "x": 1, "y": 7, "c": 11, "r": 14}, {"id": 2, "a": 1, "x": 1, "y": 7, "c": 5, "r": 10}, {"id": 3, "a": 1, "x": 3, "y": 0, "c": 8, "r": 2}, {"id": 4, "a": 1, "x": 0, "y": 4, "c": 4, "r": 8}, {"id": 5, "a": 1, "x": 2, "y": 7, "c": 6, "r": 9}, {"id": 6, "a": 1, "x": 3, "y": 0, "c": 7, "r": 3}, {"id": 7, "a": 1, "x": 2, "y": 0, "c": 6, "r": 2}, {"id": 8, "a": 0, "x": 0, "y": 4, "c": 1, "r": 0}, {"id": 9, "a": 1, "x": 1, "y": 4, "c": 5, "r": 6}, {"id": 10, "a": 0, "x": 1, "y": 4, "c": 7, "r": 7}, {"id": 11, "a": 1, "x": 2, "y": 0, "c": 6, "r": 4}], "gates": [{"id": 0, "q0": 9, "q1": 10}, {"id": 7, "q0": 0, "q1": 5}, {"id": 8, "q0": 1, "q1": 2}, {"id": 12, "q0": 3, "q1": 6}, {"id": 13, "q0": 7, "q1": 11}, {"id": 15, "q0": 4, "q1": 8}]}, {"qubits": [{"id": 0, "a": 1, "x": 1, "y": 7, "c": 6, "r": 11}, {"id": 1, "a": 0, "x": 1, "y": 7, "c": 12, "r": 15}, {"id": 2, "a": 1, "x": 0, "y": 4, "c": 5, "r": 10}, {"id": 3, "a": 1, "x": 1, "y": 1, "c": 8, "r": 2}, {"id": 4, "a": 1, "x": 0, "y": 3, "c": 4, "r": 8}, {"id": 5, "a": 1, "x": 1, "y": 4, "c": 6, "r": 9}, {"id": 6, "a": 1, "x": 1, "y": 2, "c": 7, "r": 3}, {"id": 7, "a": 1, "x": 1, "y": 1, "c": 6, "r": 2}, {"id": 8, "a": 0, "x": 0, "y": 4, "c": 0, "r": 14}, {"id": 9, "a": 1, "x": 0, "y": 3, "c": 5, "r": 6}, {"id": 10, "a": 0, "x": 1, "y": 4, "c": 3, "r": 13}, {"id": 11, "a": 1, "x": 1, "y": 2, "c": 6, "r": 4}], "gates": [{"id": 1, "q0": 4, "q1": 9}, {"id": 4, "q0": 5, "q1": 10}, {"id": 5, "q0": 0, "q1": 1}, {"id": 10, "q0": 2, "q1": 8}, {"id": 11, "q0": 6, "q1": 11}, {"id": 16, "q0": 3, "q1": 7}]}], "sat": false, "n_t": 3, "n_q": 12, "all_commutable": true, "if_Opt": false, "all_aod": false, "no_transfer": true, "pure_graph": true, "row_per_site": 3, "n_g": 18, "g_q": [[9, 10], [4, 9], [9, 11], [3, 10], [5, 10], [0, 1], [0, 2], [0, 5], [1, 2], [1, 6], [2, 8], [6, 11], [3, 6], [7, 11], [4, 5], [4, 8], [3, 7], [7, 8]], "g_s": ["CZ", "CZ", "CZ", "CZ", "CZ", "CZ", "CZ", "CZ", "CZ", "CZ", "CZ", "CZ", "CZ", "CZ", "CZ", "CZ", "CZ", "CZ"], "timestamp": "1687052981.36295", "duration": "28.435124158859253", "check_time": "26.679407358169556", "n_x": 16, "n_y": 16, "n_c": 16, "n_r": 16}